setup.cfg
setup.py
purplex/__init__.py
purplex/exception.py
purplex/grammar.py
purplex/lex.py
purplex/node.py
purplex/parse.py
purplex/token.py
purplex.egg-info/PKG-INFO
purplex.egg-info/SOURCES.txt
purplex.egg-info/dependency_links.txt
purplex.egg-info/not-zip-safe
purplex.egg-info/requires.txt
purplex.egg-info/top_level.txt