Metadata-Version: 1.0
Name: purplex
Version: 0.2.4
Summary: Pure Python lexer and parser implementation.
Home-page: https://github.com/mtomwing/purplex
Author: Michael Tom-Wing
Author-email: mtomwing@gmail.com
License: MIT
Platform: UNKNOWN
